picklebuilder/__init__.py
picklebuilder/picklebuilder.py
picklebuilder/builders/__init__.py
picklebuilder/builders/pickle.py
picklebuilder/builders/pickle64.py
picklebuilder/parsers/__init__.py
picklebuilder/parsers/pickle.py
picklebuilder/writers/__init__.py
picklebuilder/writers/pickle.py
picklebuilder/writers/pickle64.py
picklebuilder-0.2.0.dist-info/LICENSE.txt
picklebuilder-0.2.0.dist-info/METADATA
picklebuilder-0.2.0.dist-info/WHEEL
picklebuilder-0.2.0.dist-info/top_level.txt
picklebuilder-0.2.0.dist-info/RECORD
