Metadata-Version: 2.1
Name: picklebuilder
Version: 0.2.0
Summary: Sphinx extension to output pickle files.
Home-page: https://github.com/SamWilsn/picklebuilder
Download-URL: http://pypi.python.org/pypi/picklebuilder
Author: Sam Wilson
Author-email: sam.wilson@ethereum.org
License: BSD 2-Clause
Platform: any
Classifier: Development Status :: 4 - Beta
Classifier: Environment :: Console
Classifier: Framework :: Sphinx :: Extension
Classifier: Intended Audience :: Developers
Classifier: License :: OSI Approved :: BSD License
Classifier: Operating System :: OS Independent
Classifier: Programming Language :: Python :: 3
Classifier: Topic :: Documentation :: Sphinx
Classifier: Topic :: Software Development :: Documentation
Classifier: Topic :: Text Processing :: Markup :: reStructuredText
Requires-Python: >=3.7
License-File: LICENSE.txt
Requires-Dist: Sphinx (>=4.0)
Requires-Dist: docutils
